{"768662":{"hostId":"YqP0owlkQqSxmGL7AAAB","createdAt":1742588666874,"members":{"pNpEzUwoXUsVBuXyAAAD":{"id":"pNpEzUwoXUsVBuXyAAAD","name":"F","isHost":true},"i0JI9DNwdpz78JsXAAAF":{"id":"i0JI9DNwdpz78JsXAAAF","name":"F","isHost":true},"cznISG67j4RzrrdKAAAB":{"id":"cznISG67j4RzrrdKAAAB","name":"F","isHost":true}},"commonDestination":{"lat":17.387275752969963,"lng":78.35075855255128},"commonDestinationActive":true},"957665":{"hostId":"XcYmuCRc1wLTdOMSAAAB","createdAt":1742587738014,"members":{"yi9au0C__acouEK5AAAD":{"id":"yi9au0C__acouEK5AAAD","name":"F","isHost":true}},"commonDestination":{"lat":17.39462692029487,"lng":78.33960056304933},"commonDestinationActive":true}}